pinjet/__init__.py
pinjet/core/__init__.py
pinjet/core/annotations/__init__.py
pinjet/core/annotations/bootstrap.py
pinjet/core/annotations/injectable.py
pinjet/core/annotations/provider.py
pinjet/core/annotations/target.py
pinjet/core/bindings/__init__.py
pinjet/core/bindings/provider_registry.py
pinjet/core/bindings/registry.py
pinjet/core/constants/__init__.py
pinjet/core/constants/dependency_scope.py
pinjet/core/constants/element_type.py
pinjet/core/exception/__init__.py
pinjet/core/exception/exceptions.py
pinjet/core/resolver/__init__.py
pinjet/core/resolver/dependency_resolver.py
pinjet/core/resolver/singleton_bucket.py
pinjet/core/resource_scanner/__init__.py
pinjet/core/resource_scanner/resource_scanner.py
pinjet/core/types/__init__.py
pinjet/core/types/generic_types.py
pinjet/core/types/resolution_procedure.py
pinjet_core-0.0.1b1.dist-info/LICENSE
pinjet_core-0.0.1b1.dist-info/METADATA
pinjet_core-0.0.1b1.dist-info/WHEEL
pinjet_core-0.0.1b1.dist-info/top_level.txt
pinjet_core-0.0.1b1.dist-info/RECORD
