Metadata-Version: 2.1
Name: pinjet-core
Version: 0.0.1b1
Summary: Small like a pin, fast like a jet! A lightweight Dependency Injection library for python
Author: abetrack3 (Abrar Shahriar Abeed)
Author-email: <abrarshahriar2361@gmail.com>
Keywords: python,dependency injection,di framework,ioc,inversion of control
License-File: LICENSE
Requires-Dist: pinjet-common ~=1.0.2
